{"is_source_file": true, "format": "Python", "description": "This file is a Python source file intended for registering Flask blueprints related to application routes such as health checks and authentication. It is part of the routes package within a Firebase functions project.", "external_files": [], "external_methods": [], "published": [], "classes": [], "methods": [], "calls": [], "search-terms": ["routes", "blueprints", "firebase_functions", "app", "register", "health", "auth"], "state": 2, "file_id": 3, "knowledge_revision": 22, "git_revision": "9aa38642055848895c788eceb7623594dbaf5d18", "revision_history": [{"10": "bd650ea6f2e50154520313b6d92f3931b5274ada"}, {"22": "9aa38642055848895c788eceb7623594dbaf5d18"}], "ctags": [], "hash": "8f32dbc76582e4dd4e4aa34fa18f4501", "format-version": 4, "code-base-name": "firebase_functions", "filename": "firebase_functions/app/routes/__init__.py"}